xbin/__init__.py
xbin/xbin.py
xbin-0.1.5.dist-info/DESCRIPTION.rst
xbin-0.1.5.dist-info/METADATA
xbin-0.1.5.dist-info/RECORD
xbin-0.1.5.dist-info/WHEEL
xbin-0.1.5.dist-info/metadata.json
xbin-0.1.5.dist-info/top_level.txt
