Metadata-Version: 2.0
Name: xbin
Version: 0.1.5
Summary: Fancy Spatial Binning (Hashing)
Home-page: https://github.com/willsheffler/xbin
Author: Will Sheffler
Author-email: willsheffler@gmail.com
License: Apache Software License 2.0
Keywords: xbin
Platform: UNKNOWN
Classifier: Development Status :: 2 - Pre-Alpha
Classifier: Intended Audience :: Developers
Classifier: License :: OSI Approved :: Apache Software License
Classifier: Natural Language :: English
Classifier: Programming Language :: Python :: 3.5
Classifier: Programming Language :: Python :: 3.6
Requires-Dist: numpy
Requires-Dist: homog
Requires-Dist: bcc
